setup.py
src/labascraper/__init__.py
src/labascraper.egg-info/PKG-INFO
src/labascraper.egg-info/SOURCES.txt
src/labascraper.egg-info/dependency_links.txt
src/labascraper.egg-info/requires.txt
src/labascraper.egg-info/top_level.txt
src/labascraper/models/__init__.py
src/labascraper/models/author.py
src/labascraper/models/comment.py
src/labascraper/models/cryptocurrency.py
src/labascraper/scraper/__init__.py
src/labascraper/scraper/link_grabber.py
src/labascraper/scraper/page_scraper.py